[
  { "op": "add", "path": "/variants/-", "value": { "Code": "chalcopyrite" }, "file": "game:worldproperties/block/ore-graded.json" },
  { "op": "add", "path": "/variants/-", "value": { "Code": "chalcopyrite" }, "file": "game:worldproperties/block/ore-nugget.json" },
  { "op": "add", "path": "/requiredMiningTierByType/ore-*-chalcopyrite-*", "value": 2, "file": "game:blocktypes/stone/ore-graded.json" },
  { "op": "add", "path": "/combustiblePropsByType/*-chalcopyrite", "value": { "meltingPoint": 1084, "meltingDuration": 30, "smeltedRatio": 20, "smeltedStack": { "type": "item", "code": "ingot-copper" } }, "file": "game:itemtypes/resource/nugget.json" },

  { "op": "add", "path": "/allowedVariants/-", "value": "ore-poor-chalcopyrite-sandstone", "file": "game:blocktypes/stone/ore-graded.json" },
  { "op": "add", "path": "/allowedVariants/-", "value": "ore-medium-chalcopyrite-sandstone", "file": "game:blocktypes/stone/ore-graded.json" },
  { "op": "add", "path": "/allowedVariants/-", "value": "ore-poor-chalcopyrite-shale", "file": "game:blocktypes/stone/ore-graded.json" },
  { "op": "add", "path": "/allowedVariants/-", "value": "ore-medium-chalcopyrite-shale", "file": "game:blocktypes/stone/ore-graded.json" },
  { "op": "add", "path": "/allowedVariants/-", "value": "ore-poor-chalcopyrite-limestone", "file": "game:blocktypes/stone/ore-graded.json" },
  { "op": "add", "path": "/allowedVariants/-", "value": "ore-medium-chalcopyrite-limestone", "file": "game:blocktypes/stone/ore-graded.json" },
  { "op": "add", "path": "/allowedVariants/-", "value": "ore-poor-chalcopyrite-gneiss", "file": "game:blocktypes/stone/ore-graded.json" },
  { "op": "add", "path": "/allowedVariants/-", "value": "ore-medium-chalcopyrite-gneiss", "file": "game:blocktypes/stone/ore-graded.json" },
  { "op": "add", "path": "/allowedVariants/-", "value": "ore-rich-chalcopyrite-gneiss", "file": "game:blocktypes/stone/ore-graded.json" },
  { "op": "add", "path": "/allowedVariants/-", "value": "ore-bountiful-chalcopyrite-gneiss", "file": "game:blocktypes/stone/ore-graded.json" },
  { "op": "add", "path": "/allowedVariants/-", "value": "ore-poor-chalcopyrite-schist", "file": "game:blocktypes/stone/ore-graded.json" },
  { "op": "add", "path": "/allowedVariants/-", "value": "ore-medium-chalcopyrite-schist", "file": "game:blocktypes/stone/ore-graded.json" },
  { "op": "add", "path": "/allowedVariants/-", "value": "ore-rich-chalcopyrite-schist", "file": "game:blocktypes/stone/ore-graded.json" },
  { "op": "add", "path": "/allowedVariants/-", "value": "ore-bountiful-chalcopyrite-schist", "file": "game:blocktypes/stone/ore-graded.json" },
  { "op": "add", "path": "/allowedVariants/-", "value": "ore-poor-chalcopyrite-granite", "file": "game:blocktypes/stone/ore-graded.json" },
  { "op": "add", "path": "/allowedVariants/-", "value": "ore-medium-chalcopyrite-granite", "file": "game:blocktypes/stone/ore-graded.json" },
  { "op": "add", "path": "/allowedVariants/-", "value": "ore-rich-chalcopyrite-granite", "file": "game:blocktypes/stone/ore-graded.json" },
  { "op": "add", "path": "/allowedVariants/-", "value": "ore-poor-chalcopyrite-peridotite", "file": "game:blocktypes/stone/ore-graded.json" },
  { "op": "add", "path": "/allowedVariants/-", "value": "ore-medium-chalcopyrite-peridotite", "file": "game:blocktypes/stone/ore-graded.json" },
  { "op": "add", "path": "/allowedVariants/-", "value": "ore-rich-chalcopyrite-peridotite", "file": "game:blocktypes/stone/ore-graded.json" },
  { "op": "add", "path": "/allowedVariants/-", "value": "ore-poor-chalcopyrite-andesite", "file": "game:blocktypes/stone/ore-graded.json" },
  { "op": "add", "path": "/allowedVariants/-", "value": "ore-medium-chalcopyrite-andesite", "file": "game:blocktypes/stone/ore-graded.json" },
  { "op": "add", "path": "/allowedVariants/-", "value": "ore-rich-chalcopyrite-andesite", "file": "game:blocktypes/stone/ore-graded.json" },
  { "op": "add", "path": "/allowedVariants/-", "value": "ore-poor-chalcopyrite-diorite", "file": "game:blocktypes/stone/ore-graded.json" },
  { "op": "add", "path": "/allowedVariants/-", "value": "ore-medium-chalcopyrite-diorite", "file": "game:blocktypes/stone/ore-graded.json" },
  { "op": "add", "path": "/allowedVariants/-", "value": "ore-rich-chalcopyrite-diorite", "file": "game:blocktypes/stone/ore-graded.json" },
  { "op": "add", "path": "/allowedVariants/-", "value": "ore-poor-chalcopyrite-gabbro", "file": "game:blocktypes/stone/ore-graded.json" },
  { "op": "add", "path": "/allowedVariants/-", "value": "ore-medium-chalcopyrite-gabbro", "file": "game:blocktypes/stone/ore-graded.json" },
  { "op": "add", "path": "/allowedVariants/-", "value": "ore-poor-chalcopyrite-dacite", "file": "game:blocktypes/stone/ore-graded.json" },
  { "op": "add", "path": "/allowedVariants/-", "value": "ore-medium-chalcopyrite-dacite", "file": "game:blocktypes/stone/ore-graded.json" },
  { "op": "add", "path": "/allowedVariants/-", "value": "ore-rich-chalcopyrite-dacite", "file": "game:blocktypes/stone/ore-graded.json" },
  { "op": "add", "path": "/allowedVariants/-", "value": "ore-poor-chalcopyrite-rhyolite", "file": "game:blocktypes/stone/ore-graded.json" },
  { "op": "add", "path": "/allowedVariants/-", "value": "ore-medium-chalcopyrite-rhyolite", "file": "game:blocktypes/stone/ore-graded.json" },
  { "op": "add", "path": "/allowedVariants/-", "value": "ore-rich-chalcopyrite-rhyolite", "file": "game:blocktypes/stone/ore-graded.json" },

  { "op": "add", "path": "/allowedVariants/-", "value": "looseores-chalcopyrite-sandstone-free", "file": "game:blocktypes/stone/looseores.json" },
  { "op": "add", "path": "/allowedVariants/-", "value": "looseores-chalcopyrite-shale-free", "file": "game:blocktypes/stone/looseores.json" },
  { "op": "add", "path": "/allowedVariants/-", "value": "looseores-chalcopyrite-limestone-free", "file": "game:blocktypes/stone/looseores.json" },
  { "op": "add", "path": "/allowedVariants/-", "value": "looseores-chalcopyrite-gneiss-free", "file": "game:blocktypes/stone/looseores.json" },
  { "op": "add", "path": "/allowedVariants/-", "value": "looseores-chalcopyrite-schist-free", "file": "game:blocktypes/stone/looseores.json" },
  { "op": "add", "path": "/allowedVariants/-", "value": "looseores-chalcopyrite-granite-free", "file": "game:blocktypes/stone/looseores.json" },
  { "op": "add", "path": "/allowedVariants/-", "value": "looseores-chalcopyrite-peridotite-free", "file": "game:blocktypes/stone/looseores.json" },
  { "op": "add", "path": "/allowedVariants/-", "value": "looseores-chalcopyrite-andesite-free", "file": "game:blocktypes/stone/looseores.json" },
  { "op": "add", "path": "/allowedVariants/-", "value": "looseores-chalcopyrite-diorite-free", "file": "game:blocktypes/stone/looseores.json" },
  { "op": "add", "path": "/allowedVariants/-", "value": "looseores-chalcopyrite-gabbro-free", "file": "game:blocktypes/stone/looseores.json" },
  { "op": "add", "path": "/allowedVariants/-", "value": "looseores-chalcopyrite-dacite-free", "file": "game:blocktypes/stone/looseores.json" },
  { "op": "add", "path": "/allowedVariants/-", "value": "looseores-chalcopyrite-rhyolite-free", "file": "game:blocktypes/stone/looseores.json" },

  { "op": "add", "path": "/allowedVariants/-", "value": "ore-poor-chalcopyrite-sandstone", "file": "game:itemtypes/resource/ore-graded.json" },
  { "op": "add", "path": "/allowedVariants/-", "value": "ore-medium-chalcopyrite-sandstone", "file": "game:itemtypes/resource/ore-graded.json" },
  { "op": "add", "path": "/allowedVariants/-", "value": "ore-poor-chalcopyrite-shale", "file": "game:itemtypes/resource/ore-graded.json" },
  { "op": "add", "path": "/allowedVariants/-", "value": "ore-medium-chalcopyrite-shale", "file": "game:itemtypes/resource/ore-graded.json" },
  { "op": "add", "path": "/allowedVariants/-", "value": "ore-poor-chalcopyrite-limestone", "file": "game:itemtypes/resource/ore-graded.json" },
  { "op": "add", "path": "/allowedVariants/-", "value": "ore-medium-chalcopyrite-limestone", "file": "game:itemtypes/resource/ore-graded.json" },
  { "op": "add", "path": "/allowedVariants/-", "value": "ore-poor-chalcopyrite-gneiss", "file": "game:itemtypes/resource/ore-graded.json" },
  { "op": "add", "path": "/allowedVariants/-", "value": "ore-medium-chalcopyrite-gneiss", "file": "game:itemtypes/resource/ore-graded.json" },
  { "op": "add", "path": "/allowedVariants/-", "value": "ore-rich-chalcopyrite-gneiss", "file": "game:itemtypes/resource/ore-graded.json" },
  { "op": "add", "path": "/allowedVariants/-", "value": "ore-bountiful-chalcopyrite-gneiss", "file": "game:itemtypes/resource/ore-graded.json" },
  { "op": "add", "path": "/allowedVariants/-", "value": "ore-poor-chalcopyrite-schist", "file": "game:itemtypes/resource/ore-graded.json" },
  { "op": "add", "path": "/allowedVariants/-", "value": "ore-medium-chalcopyrite-schist", "file": "game:itemtypes/resource/ore-graded.json" },
  { "op": "add", "path": "/allowedVariants/-", "value": "ore-rich-chalcopyrite-schist", "file": "game:itemtypes/resource/ore-graded.json" },
  { "op": "add", "path": "/allowedVariants/-", "value": "ore-bountiful-chalcopyrite-schist", "file": "game:itemtypes/resource/ore-graded.json" },
  { "op": "add", "path": "/allowedVariants/-", "value": "ore-poor-chalcopyrite-granite", "file": "game:itemtypes/resource/ore-graded.json" },
  { "op": "add", "path": "/allowedVariants/-", "value": "ore-medium-chalcopyrite-granite", "file": "game:itemtypes/resource/ore-graded.json" },
  { "op": "add", "path": "/allowedVariants/-", "value": "ore-rich-chalcopyrite-granite", "file": "game:itemtypes/resource/ore-graded.json" },
  { "op": "add", "path": "/allowedVariants/-", "value": "ore-poor-chalcopyrite-peridotite", "file": "game:itemtypes/resource/ore-graded.json" },
  { "op": "add", "path": "/allowedVariants/-", "value": "ore-medium-chalcopyrite-peridotite", "file": "game:itemtypes/resource/ore-graded.json" },
  { "op": "add", "path": "/allowedVariants/-", "value": "ore-rich-chalcopyrite-peridotite", "file": "game:itemtypes/resource/ore-graded.json" },
  { "op": "add", "path": "/allowedVariants/-", "value": "ore-poor-chalcopyrite-andesite", "file": "game:itemtypes/resource/ore-graded.json" },
  { "op": "add", "path": "/allowedVariants/-", "value": "ore-medium-chalcopyrite-andesite", "file": "game:itemtypes/resource/ore-graded.json" },
  { "op": "add", "path": "/allowedVariants/-", "value": "ore-rich-chalcopyrite-andesite", "file": "game:itemtypes/resource/ore-graded.json" },
  { "op": "add", "path": "/allowedVariants/-", "value": "ore-poor-chalcopyrite-diorite", "file": "game:itemtypes/resource/ore-graded.json" },
  { "op": "add", "path": "/allowedVariants/-", "value": "ore-medium-chalcopyrite-diorite", "file": "game:itemtypes/resource/ore-graded.json" },
  { "op": "add", "path": "/allowedVariants/-", "value": "ore-rich-chalcopyrite-diorite", "file": "game:itemtypes/resource/ore-graded.json" },
  { "op": "add", "path": "/allowedVariants/-", "value": "ore-poor-chalcopyrite-gabbro", "file": "game:itemtypes/resource/ore-graded.json" },
  { "op": "add", "path": "/allowedVariants/-", "value": "ore-medium-chalcopyrite-gabbro", "file": "game:itemtypes/resource/ore-graded.json" },
  { "op": "add", "path": "/allowedVariants/-", "value": "ore-poor-chalcopyrite-dacite", "file": "game:itemtypes/resource/ore-graded.json" },
  { "op": "add", "path": "/allowedVariants/-", "value": "ore-medium-chalcopyrite-dacite", "file": "game:itemtypes/resource/ore-graded.json" },
  { "op": "add", "path": "/allowedVariants/-", "value": "ore-rich-chalcopyrite-dacite", "file": "game:itemtypes/resource/ore-graded.json" },
  { "op": "add", "path": "/allowedVariants/-", "value": "ore-poor-chalcopyrite-rhyolite", "file": "game:itemtypes/resource/ore-graded.json" },
  { "op": "add", "path": "/allowedVariants/-", "value": "ore-medium-chalcopyrite-rhyolite", "file": "game:itemtypes/resource/ore-graded.json" },
  { "op": "add", "path": "/allowedVariants/-", "value": "ore-rich-chalcopyrite-rhyolite", "file": "game:itemtypes/resource/ore-graded.json" },

  { "op": "add", "path": "/allowedVariants/-", "value": "crystalizedore-poor-chalcopyrite-sandstone", "file": "game:itemtypes/resource/crystalizedore-graded.json" },
  { "op": "add", "path": "/allowedVariants/-", "value": "crystalizedore-medium-chalcopyrite-sandstone", "file": "game:itemtypes/resource/crystalizedore-graded.json" },
  { "op": "add", "path": "/allowedVariants/-", "value": "crystalizedore-poor-chalcopyrite-shale", "file": "game:itemtypes/resource/crystalizedore-graded.json" },
  { "op": "add", "path": "/allowedVariants/-", "value": "crystalizedore-medium-chalcopyrite-shale", "file": "game:itemtypes/resource/crystalizedore-graded.json" },
  { "op": "add", "path": "/allowedVariants/-", "value": "crystalizedore-poor-chalcopyrite-limestone", "file": "game:itemtypes/resource/crystalizedore-graded.json" },
  { "op": "add", "path": "/allowedVariants/-", "value": "crystalizedore-medium-chalcopyrite-limestone", "file": "game:itemtypes/resource/crystalizedore-graded.json" },
  { "op": "add", "path": "/allowedVariants/-", "value": "crystalizedore-poor-chalcopyrite-gneiss", "file": "game:itemtypes/resource/crystalizedore-graded.json" },
  { "op": "add", "path": "/allowedVariants/-", "value": "crystalizedore-medium-chalcopyrite-gneiss", "file": "game:itemtypes/resource/crystalizedore-graded.json" },
  { "op": "add", "path": "/allowedVariants/-", "value": "crystalizedore-rich-chalcopyrite-gneiss", "file": "game:itemtypes/resource/crystalizedore-graded.json" },
  { "op": "add", "path": "/allowedVariants/-", "value": "crystalizedore-bountiful-chalcopyrite-gneiss", "file": "game:itemtypes/resource/crystalizedore-graded.json" },
  { "op": "add", "path": "/allowedVariants/-", "value": "crystalizedore-poor-chalcopyrite-schist", "file": "game:itemtypes/resource/crystalizedore-graded.json" },
  { "op": "add", "path": "/allowedVariants/-", "value": "crystalizedore-medium-chalcopyrite-schist", "file": "game:itemtypes/resource/crystalizedore-graded.json" },
  { "op": "add", "path": "/allowedVariants/-", "value": "crystalizedore-rich-chalcopyrite-schist", "file": "game:itemtypes/resource/crystalizedore-graded.json" },
  { "op": "add", "path": "/allowedVariants/-", "value": "crystalizedore-bountiful-chalcopyrite-schist", "file": "game:itemtypes/resource/crystalizedore-graded.json" },
  { "op": "add", "path": "/allowedVariants/-", "value": "crystalizedore-poor-chalcopyrite-granite", "file": "game:itemtypes/resource/crystalizedore-graded.json" },
  { "op": "add", "path": "/allowedVariants/-", "value": "crystalizedore-medium-chalcopyrite-granite", "file": "game:itemtypes/resource/crystalizedore-graded.json" },
  { "op": "add", "path": "/allowedVariants/-", "value": "crystalizedore-rich-chalcopyrite-granite", "file": "game:itemtypes/resource/crystalizedore-graded.json" },
  { "op": "add", "path": "/allowedVariants/-", "value": "crystalizedore-poor-chalcopyrite-peridotite", "file": "game:itemtypes/resource/crystalizedore-graded.json" },
  { "op": "add", "path": "/allowedVariants/-", "value": "crystalizedore-medium-chalcopyrite-peridotite", "file": "game:itemtypes/resource/crystalizedore-graded.json" },
  { "op": "add", "path": "/allowedVariants/-", "value": "crystalizedore-rich-chalcopyrite-peridotite", "file": "game:itemtypes/resource/crystalizedore-graded.json" },
  { "op": "add", "path": "/allowedVariants/-", "value": "crystalizedore-poor-chalcopyrite-andesite", "file": "game:itemtypes/resource/crystalizedore-graded.json" },
  { "op": "add", "path": "/allowedVariants/-", "value": "crystalizedore-medium-chalcopyrite-andesite", "file": "game:itemtypes/resource/crystalizedore-graded.json" },
  { "op": "add", "path": "/allowedVariants/-", "value": "crystalizedore-rich-chalcopyrite-andesite", "file": "game:itemtypes/resource/crystalizedore-graded.json" },
  { "op": "add", "path": "/allowedVariants/-", "value": "crystalizedore-poor-chalcopyrite-diorite", "file": "game:itemtypes/resource/crystalizedore-graded.json" },
  { "op": "add", "path": "/allowedVariants/-", "value": "crystalizedore-medium-chalcopyrite-diorite", "file": "game:itemtypes/resource/crystalizedore-graded.json" },
  { "op": "add", "path": "/allowedVariants/-", "value": "crystalizedore-rich-chalcopyrite-diorite", "file": "game:itemtypes/resource/crystalizedore-graded.json" },
  { "op": "add", "path": "/allowedVariants/-", "value": "crystalizedore-poor-chalcopyrite-gabbro", "file": "game:itemtypes/resource/crystalizedore-graded.json" },
  { "op": "add", "path": "/allowedVariants/-", "value": "crystalizedore-medium-chalcopyrite-gabbro", "file": "game:itemtypes/resource/crystalizedore-graded.json" },
  { "op": "add", "path": "/allowedVariants/-", "value": "crystalizedore-poor-chalcopyrite-dacite", "file": "game:itemtypes/resource/crystalizedore-graded.json" },
  { "op": "add", "path": "/allowedVariants/-", "value": "crystalizedore-medium-chalcopyrite-dacite", "file": "game:itemtypes/resource/crystalizedore-graded.json" },
  { "op": "add", "path": "/allowedVariants/-", "value": "crystalizedore-rich-chalcopyrite-dacite", "file": "game:itemtypes/resource/crystalizedore-graded.json" },
  { "op": "add", "path": "/allowedVariants/-", "value": "crystalizedore-poor-chalcopyrite-rhyolite", "file": "game:itemtypes/resource/crystalizedore-graded.json" },
  { "op": "add", "path": "/allowedVariants/-", "value": "crystalizedore-medium-chalcopyrite-rhyolite", "file": "game:itemtypes/resource/crystalizedore-graded.json" },
  { "op": "add", "path": "/allowedVariants/-", "value": "crystalizedore-rich-chalcopyrite-rhyolite", "file": "game:itemtypes/resource/crystalizedore-graded.json" },

  // ==== GEOADDONS: chalcocite + pyrite childDeposit variants (poor+medium in all chalcopyrite rocks) ====

  // --- chalcocite: blocktypes/ore-graded ---
  { "op": "add", "path": "/allowedVariants/-", "value": "ore-poor-chalcocite-sandstone", "file": "game:blocktypes/stone/ore-graded.json", "dependsOn": [{ "modid": "geoaddons" }] },
  { "op": "add", "path": "/allowedVariants/-", "value": "ore-medium-chalcocite-sandstone", "file": "game:blocktypes/stone/ore-graded.json", "dependsOn": [{ "modid": "geoaddons" }] },
  { "op": "add", "path": "/allowedVariants/-", "value": "ore-poor-chalcocite-shale", "file": "game:blocktypes/stone/ore-graded.json", "dependsOn": [{ "modid": "geoaddons" }] },
  { "op": "add", "path": "/allowedVariants/-", "value": "ore-medium-chalcocite-shale", "file": "game:blocktypes/stone/ore-graded.json", "dependsOn": [{ "modid": "geoaddons" }] },
  { "op": "add", "path": "/allowedVariants/-", "value": "ore-poor-chalcocite-limestone", "file": "game:blocktypes/stone/ore-graded.json", "dependsOn": [{ "modid": "geoaddons" }] },
  { "op": "add", "path": "/allowedVariants/-", "value": "ore-medium-chalcocite-limestone", "file": "game:blocktypes/stone/ore-graded.json", "dependsOn": [{ "modid": "geoaddons" }] },
  { "op": "add", "path": "/allowedVariants/-", "value": "ore-poor-chalcocite-andesite", "file": "game:blocktypes/stone/ore-graded.json", "dependsOn": [{ "modid": "geoaddons" }] },
  { "op": "add", "path": "/allowedVariants/-", "value": "ore-medium-chalcocite-andesite", "file": "game:blocktypes/stone/ore-graded.json", "dependsOn": [{ "modid": "geoaddons" }] },
  { "op": "add", "path": "/allowedVariants/-", "value": "ore-poor-chalcocite-granite", "file": "game:blocktypes/stone/ore-graded.json", "dependsOn": [{ "modid": "geoaddons" }] },
  { "op": "add", "path": "/allowedVariants/-", "value": "ore-medium-chalcocite-granite", "file": "game:blocktypes/stone/ore-graded.json", "dependsOn": [{ "modid": "geoaddons" }] },
  { "op": "add", "path": "/allowedVariants/-", "value": "ore-poor-chalcocite-peridotite", "file": "game:blocktypes/stone/ore-graded.json", "dependsOn": [{ "modid": "geoaddons" }] },
  { "op": "add", "path": "/allowedVariants/-", "value": "ore-medium-chalcocite-peridotite", "file": "game:blocktypes/stone/ore-graded.json", "dependsOn": [{ "modid": "geoaddons" }] },
  { "op": "add", "path": "/allowedVariants/-", "value": "ore-poor-chalcocite-gneiss", "file": "game:blocktypes/stone/ore-graded.json", "dependsOn": [{ "modid": "geoaddons" }] },
  { "op": "add", "path": "/allowedVariants/-", "value": "ore-medium-chalcocite-gneiss", "file": "game:blocktypes/stone/ore-graded.json", "dependsOn": [{ "modid": "geoaddons" }] },
  { "op": "add", "path": "/allowedVariants/-", "value": "ore-poor-chalcocite-schist", "file": "game:blocktypes/stone/ore-graded.json", "dependsOn": [{ "modid": "geoaddons" }] },
  { "op": "add", "path": "/allowedVariants/-", "value": "ore-medium-chalcocite-schist", "file": "game:blocktypes/stone/ore-graded.json", "dependsOn": [{ "modid": "geoaddons" }] },
  { "op": "add", "path": "/allowedVariants/-", "value": "ore-poor-chalcocite-diorite", "file": "game:blocktypes/stone/ore-graded.json", "dependsOn": [{ "modid": "geoaddons" }] },
  { "op": "add", "path": "/allowedVariants/-", "value": "ore-medium-chalcocite-diorite", "file": "game:blocktypes/stone/ore-graded.json", "dependsOn": [{ "modid": "geoaddons" }] },
  { "op": "add", "path": "/allowedVariants/-", "value": "ore-poor-chalcocite-gabbro", "file": "game:blocktypes/stone/ore-graded.json", "dependsOn": [{ "modid": "geoaddons" }] },
  { "op": "add", "path": "/allowedVariants/-", "value": "ore-medium-chalcocite-gabbro", "file": "game:blocktypes/stone/ore-graded.json", "dependsOn": [{ "modid": "geoaddons" }] },
  { "op": "add", "path": "/allowedVariants/-", "value": "ore-poor-chalcocite-dacite", "file": "game:blocktypes/stone/ore-graded.json", "dependsOn": [{ "modid": "geoaddons" }] },
  { "op": "add", "path": "/allowedVariants/-", "value": "ore-medium-chalcocite-dacite", "file": "game:blocktypes/stone/ore-graded.json", "dependsOn": [{ "modid": "geoaddons" }] },
  { "op": "add", "path": "/allowedVariants/-", "value": "ore-poor-chalcocite-rhyolite", "file": "game:blocktypes/stone/ore-graded.json", "dependsOn": [{ "modid": "geoaddons" }] },
  { "op": "add", "path": "/allowedVariants/-", "value": "ore-medium-chalcocite-rhyolite", "file": "game:blocktypes/stone/ore-graded.json", "dependsOn": [{ "modid": "geoaddons" }] },
  // --- chalcocite: itemtypes/ore-graded ---
  { "op": "add", "path": "/allowedVariants/-", "value": "ore-poor-chalcocite-sandstone", "file": "game:itemtypes/resource/ore-graded.json", "dependsOn": [{ "modid": "geoaddons" }] },
  { "op": "add", "path": "/allowedVariants/-", "value": "ore-medium-chalcocite-sandstone", "file": "game:itemtypes/resource/ore-graded.json", "dependsOn": [{ "modid": "geoaddons" }] },
  { "op": "add", "path": "/allowedVariants/-", "value": "ore-poor-chalcocite-shale", "file": "game:itemtypes/resource/ore-graded.json", "dependsOn": [{ "modid": "geoaddons" }] },
  { "op": "add", "path": "/allowedVariants/-", "value": "ore-medium-chalcocite-shale", "file": "game:itemtypes/resource/ore-graded.json", "dependsOn": [{ "modid": "geoaddons" }] },
  { "op": "add", "path": "/allowedVariants/-", "value": "ore-poor-chalcocite-limestone", "file": "game:itemtypes/resource/ore-graded.json", "dependsOn": [{ "modid": "geoaddons" }] },
  { "op": "add", "path": "/allowedVariants/-", "value": "ore-medium-chalcocite-limestone", "file": "game:itemtypes/resource/ore-graded.json", "dependsOn": [{ "modid": "geoaddons" }] },
  { "op": "add", "path": "/allowedVariants/-", "value": "ore-poor-chalcocite-andesite", "file": "game:itemtypes/resource/ore-graded.json", "dependsOn": [{ "modid": "geoaddons" }] },
  { "op": "add", "path": "/allowedVariants/-", "value": "ore-medium-chalcocite-andesite", "file": "game:itemtypes/resource/ore-graded.json", "dependsOn": [{ "modid": "geoaddons" }] },
  { "op": "add", "path": "/allowedVariants/-", "value": "ore-poor-chalcocite-granite", "file": "game:itemtypes/resource/ore-graded.json", "dependsOn": [{ "modid": "geoaddons" }] },
  { "op": "add", "path": "/allowedVariants/-", "value": "ore-medium-chalcocite-granite", "file": "game:itemtypes/resource/ore-graded.json", "dependsOn": [{ "modid": "geoaddons" }] },
  { "op": "add", "path": "/allowedVariants/-", "value": "ore-poor-chalcocite-peridotite", "file": "game:itemtypes/resource/ore-graded.json", "dependsOn": [{ "modid": "geoaddons" }] },
  { "op": "add", "path": "/allowedVariants/-", "value": "ore-medium-chalcocite-peridotite", "file": "game:itemtypes/resource/ore-graded.json", "dependsOn": [{ "modid": "geoaddons" }] },
  { "op": "add", "path": "/allowedVariants/-", "value": "ore-poor-chalcocite-gneiss", "file": "game:itemtypes/resource/ore-graded.json", "dependsOn": [{ "modid": "geoaddons" }] },
  { "op": "add", "path": "/allowedVariants/-", "value": "ore-medium-chalcocite-gneiss", "file": "game:itemtypes/resource/ore-graded.json", "dependsOn": [{ "modid": "geoaddons" }] },
  { "op": "add", "path": "/allowedVariants/-", "value": "ore-poor-chalcocite-schist", "file": "game:itemtypes/resource/ore-graded.json", "dependsOn": [{ "modid": "geoaddons" }] },
  { "op": "add", "path": "/allowedVariants/-", "value": "ore-medium-chalcocite-schist", "file": "game:itemtypes/resource/ore-graded.json", "dependsOn": [{ "modid": "geoaddons" }] },
  { "op": "add", "path": "/allowedVariants/-", "value": "ore-poor-chalcocite-diorite", "file": "game:itemtypes/resource/ore-graded.json", "dependsOn": [{ "modid": "geoaddons" }] },
  { "op": "add", "path": "/allowedVariants/-", "value": "ore-medium-chalcocite-diorite", "file": "game:itemtypes/resource/ore-graded.json", "dependsOn": [{ "modid": "geoaddons" }] },
  { "op": "add", "path": "/allowedVariants/-", "value": "ore-poor-chalcocite-gabbro", "file": "game:itemtypes/resource/ore-graded.json", "dependsOn": [{ "modid": "geoaddons" }] },
  { "op": "add", "path": "/allowedVariants/-", "value": "ore-medium-chalcocite-gabbro", "file": "game:itemtypes/resource/ore-graded.json", "dependsOn": [{ "modid": "geoaddons" }] },
  { "op": "add", "path": "/allowedVariants/-", "value": "ore-poor-chalcocite-dacite", "file": "game:itemtypes/resource/ore-graded.json", "dependsOn": [{ "modid": "geoaddons" }] },
  { "op": "add", "path": "/allowedVariants/-", "value": "ore-medium-chalcocite-dacite", "file": "game:itemtypes/resource/ore-graded.json", "dependsOn": [{ "modid": "geoaddons" }] },
  { "op": "add", "path": "/allowedVariants/-", "value": "ore-poor-chalcocite-rhyolite", "file": "game:itemtypes/resource/ore-graded.json", "dependsOn": [{ "modid": "geoaddons" }] },
  { "op": "add", "path": "/allowedVariants/-", "value": "ore-medium-chalcocite-rhyolite", "file": "game:itemtypes/resource/ore-graded.json", "dependsOn": [{ "modid": "geoaddons" }] },
  // --- chalcocite: crystalizedore-graded ---
  { "op": "add", "path": "/allowedVariants/-", "value": "crystalizedore-poor-chalcocite-sandstone", "file": "game:itemtypes/resource/crystalizedore-graded.json", "dependsOn": [{ "modid": "geoaddons" }] },
  { "op": "add", "path": "/allowedVariants/-", "value": "crystalizedore-medium-chalcocite-sandstone", "file": "game:itemtypes/resource/crystalizedore-graded.json", "dependsOn": [{ "modid": "geoaddons" }] },
  { "op": "add", "path": "/allowedVariants/-", "value": "crystalizedore-poor-chalcocite-shale", "file": "game:itemtypes/resource/crystalizedore-graded.json", "dependsOn": [{ "modid": "geoaddons" }] },
  { "op": "add", "path": "/allowedVariants/-", "value": "crystalizedore-medium-chalcocite-shale", "file": "game:itemtypes/resource/crystalizedore-graded.json", "dependsOn": [{ "modid": "geoaddons" }] },
  { "op": "add", "path": "/allowedVariants/-", "value": "crystalizedore-poor-chalcocite-limestone", "file": "game:itemtypes/resource/crystalizedore-graded.json", "dependsOn": [{ "modid": "geoaddons" }] },
  { "op": "add", "path": "/allowedVariants/-", "value": "crystalizedore-medium-chalcocite-limestone", "file": "game:itemtypes/resource/crystalizedore-graded.json", "dependsOn": [{ "modid": "geoaddons" }] },
  { "op": "add", "path": "/allowedVariants/-", "value": "crystalizedore-poor-chalcocite-andesite", "file": "game:itemtypes/resource/crystalizedore-graded.json", "dependsOn": [{ "modid": "geoaddons" }] },
  { "op": "add", "path": "/allowedVariants/-", "value": "crystalizedore-medium-chalcocite-andesite", "file": "game:itemtypes/resource/crystalizedore-graded.json", "dependsOn": [{ "modid": "geoaddons" }] },
  { "op": "add", "path": "/allowedVariants/-", "value": "crystalizedore-poor-chalcocite-granite", "file": "game:itemtypes/resource/crystalizedore-graded.json", "dependsOn": [{ "modid": "geoaddons" }] },
  { "op": "add", "path": "/allowedVariants/-", "value": "crystalizedore-medium-chalcocite-granite", "file": "game:itemtypes/resource/crystalizedore-graded.json", "dependsOn": [{ "modid": "geoaddons" }] },
  { "op": "add", "path": "/allowedVariants/-", "value": "crystalizedore-poor-chalcocite-peridotite", "file": "game:itemtypes/resource/crystalizedore-graded.json", "dependsOn": [{ "modid": "geoaddons" }] },
  { "op": "add", "path": "/allowedVariants/-", "value": "crystalizedore-medium-chalcocite-peridotite", "file": "game:itemtypes/resource/crystalizedore-graded.json", "dependsOn": [{ "modid": "geoaddons" }] },
  { "op": "add", "path": "/allowedVariants/-", "value": "crystalizedore-poor-chalcocite-gneiss", "file": "game:itemtypes/resource/crystalizedore-graded.json", "dependsOn": [{ "modid": "geoaddons" }] },
  { "op": "add", "path": "/allowedVariants/-", "value": "crystalizedore-medium-chalcocite-gneiss", "file": "game:itemtypes/resource/crystalizedore-graded.json", "dependsOn": [{ "modid": "geoaddons" }] },
  { "op": "add", "path": "/allowedVariants/-", "value": "crystalizedore-poor-chalcocite-schist", "file": "game:itemtypes/resource/crystalizedore-graded.json", "dependsOn": [{ "modid": "geoaddons" }] },
  { "op": "add", "path": "/allowedVariants/-", "value": "crystalizedore-medium-chalcocite-schist", "file": "game:itemtypes/resource/crystalizedore-graded.json", "dependsOn": [{ "modid": "geoaddons" }] },
  { "op": "add", "path": "/allowedVariants/-", "value": "crystalizedore-poor-chalcocite-diorite", "file": "game:itemtypes/resource/crystalizedore-graded.json", "dependsOn": [{ "modid": "geoaddons" }] },
  { "op": "add", "path": "/allowedVariants/-", "value": "crystalizedore-medium-chalcocite-diorite", "file": "game:itemtypes/resource/crystalizedore-graded.json", "dependsOn": [{ "modid": "geoaddons" }] },
  { "op": "add", "path": "/allowedVariants/-", "value": "crystalizedore-poor-chalcocite-gabbro", "file": "game:itemtypes/resource/crystalizedore-graded.json", "dependsOn": [{ "modid": "geoaddons" }] },
  { "op": "add", "path": "/allowedVariants/-", "value": "crystalizedore-medium-chalcocite-gabbro", "file": "game:itemtypes/resource/crystalizedore-graded.json", "dependsOn": [{ "modid": "geoaddons" }] },
  { "op": "add", "path": "/allowedVariants/-", "value": "crystalizedore-poor-chalcocite-dacite", "file": "game:itemtypes/resource/crystalizedore-graded.json", "dependsOn": [{ "modid": "geoaddons" }] },
  { "op": "add", "path": "/allowedVariants/-", "value": "crystalizedore-medium-chalcocite-dacite", "file": "game:itemtypes/resource/crystalizedore-graded.json", "dependsOn": [{ "modid": "geoaddons" }] },
  { "op": "add", "path": "/allowedVariants/-", "value": "crystalizedore-poor-chalcocite-rhyolite", "file": "game:itemtypes/resource/crystalizedore-graded.json", "dependsOn": [{ "modid": "geoaddons" }] },
  { "op": "add", "path": "/allowedVariants/-", "value": "crystalizedore-medium-chalcocite-rhyolite", "file": "game:itemtypes/resource/crystalizedore-graded.json", "dependsOn": [{ "modid": "geoaddons" }] },

  // --- pyrite: blocktypes/ore-graded ---
  { "op": "add", "path": "/allowedVariants/-", "value": "ore-poor-pyrite-sandstone", "file": "game:blocktypes/stone/ore-graded.json", "dependsOn": [{ "modid": "geoaddons" }] },
  { "op": "add", "path": "/allowedVariants/-", "value": "ore-medium-pyrite-sandstone", "file": "game:blocktypes/stone/ore-graded.json", "dependsOn": [{ "modid": "geoaddons" }] },
  { "op": "add", "path": "/allowedVariants/-", "value": "ore-poor-pyrite-shale", "file": "game:blocktypes/stone/ore-graded.json", "dependsOn": [{ "modid": "geoaddons" }] },
  { "op": "add", "path": "/allowedVariants/-", "value": "ore-medium-pyrite-shale", "file": "game:blocktypes/stone/ore-graded.json", "dependsOn": [{ "modid": "geoaddons" }] },
  { "op": "add", "path": "/allowedVariants/-", "value": "ore-poor-pyrite-limestone", "file": "game:blocktypes/stone/ore-graded.json", "dependsOn": [{ "modid": "geoaddons" }] },
  { "op": "add", "path": "/allowedVariants/-", "value": "ore-medium-pyrite-limestone", "file": "game:blocktypes/stone/ore-graded.json", "dependsOn": [{ "modid": "geoaddons" }] },
  { "op": "add", "path": "/allowedVariants/-", "value": "ore-poor-pyrite-andesite", "file": "game:blocktypes/stone/ore-graded.json", "dependsOn": [{ "modid": "geoaddons" }] },
  { "op": "add", "path": "/allowedVariants/-", "value": "ore-medium-pyrite-andesite", "file": "game:blocktypes/stone/ore-graded.json", "dependsOn": [{ "modid": "geoaddons" }] },
  { "op": "add", "path": "/allowedVariants/-", "value": "ore-poor-pyrite-granite", "file": "game:blocktypes/stone/ore-graded.json", "dependsOn": [{ "modid": "geoaddons" }] },
  { "op": "add", "path": "/allowedVariants/-", "value": "ore-medium-pyrite-granite", "file": "game:blocktypes/stone/ore-graded.json", "dependsOn": [{ "modid": "geoaddons" }] },
  { "op": "add", "path": "/allowedVariants/-", "value": "ore-poor-pyrite-peridotite", "file": "game:blocktypes/stone/ore-graded.json", "dependsOn": [{ "modid": "geoaddons" }] },
  { "op": "add", "path": "/allowedVariants/-", "value": "ore-medium-pyrite-peridotite", "file": "game:blocktypes/stone/ore-graded.json", "dependsOn": [{ "modid": "geoaddons" }] },
  { "op": "add", "path": "/allowedVariants/-", "value": "ore-poor-pyrite-gneiss", "file": "game:blocktypes/stone/ore-graded.json", "dependsOn": [{ "modid": "geoaddons" }] },
  { "op": "add", "path": "/allowedVariants/-", "value": "ore-medium-pyrite-gneiss", "file": "game:blocktypes/stone/ore-graded.json", "dependsOn": [{ "modid": "geoaddons" }] },
  { "op": "add", "path": "/allowedVariants/-", "value": "ore-poor-pyrite-schist", "file": "game:blocktypes/stone/ore-graded.json", "dependsOn": [{ "modid": "geoaddons" }] },
  { "op": "add", "path": "/allowedVariants/-", "value": "ore-medium-pyrite-schist", "file": "game:blocktypes/stone/ore-graded.json", "dependsOn": [{ "modid": "geoaddons" }] },
  { "op": "add", "path": "/allowedVariants/-", "value": "ore-poor-pyrite-diorite", "file": "game:blocktypes/stone/ore-graded.json", "dependsOn": [{ "modid": "geoaddons" }] },
  { "op": "add", "path": "/allowedVariants/-", "value": "ore-medium-pyrite-diorite", "file": "game:blocktypes/stone/ore-graded.json", "dependsOn": [{ "modid": "geoaddons" }] },
  { "op": "add", "path": "/allowedVariants/-", "value": "ore-poor-pyrite-gabbro", "file": "game:blocktypes/stone/ore-graded.json", "dependsOn": [{ "modid": "geoaddons" }] },
  { "op": "add", "path": "/allowedVariants/-", "value": "ore-medium-pyrite-gabbro", "file": "game:blocktypes/stone/ore-graded.json", "dependsOn": [{ "modid": "geoaddons" }] },
  { "op": "add", "path": "/allowedVariants/-", "value": "ore-poor-pyrite-dacite", "file": "game:blocktypes/stone/ore-graded.json", "dependsOn": [{ "modid": "geoaddons" }] },
  { "op": "add", "path": "/allowedVariants/-", "value": "ore-medium-pyrite-dacite", "file": "game:blocktypes/stone/ore-graded.json", "dependsOn": [{ "modid": "geoaddons" }] },
  { "op": "add", "path": "/allowedVariants/-", "value": "ore-poor-pyrite-rhyolite", "file": "game:blocktypes/stone/ore-graded.json", "dependsOn": [{ "modid": "geoaddons" }] },
  { "op": "add", "path": "/allowedVariants/-", "value": "ore-medium-pyrite-rhyolite", "file": "game:blocktypes/stone/ore-graded.json", "dependsOn": [{ "modid": "geoaddons" }] },
  // --- pyrite: itemtypes/ore-graded ---
  { "op": "add", "path": "/allowedVariants/-", "value": "ore-poor-pyrite-sandstone", "file": "game:itemtypes/resource/ore-graded.json", "dependsOn": [{ "modid": "geoaddons" }] },
  { "op": "add", "path": "/allowedVariants/-", "value": "ore-medium-pyrite-sandstone", "file": "game:itemtypes/resource/ore-graded.json", "dependsOn": [{ "modid": "geoaddons" }] },
  { "op": "add", "path": "/allowedVariants/-", "value": "ore-poor-pyrite-shale", "file": "game:itemtypes/resource/ore-graded.json", "dependsOn": [{ "modid": "geoaddons" }] },
  { "op": "add", "path": "/allowedVariants/-", "value": "ore-medium-pyrite-shale", "file": "game:itemtypes/resource/ore-graded.json", "dependsOn": [{ "modid": "geoaddons" }] },
  { "op": "add", "path": "/allowedVariants/-", "value": "ore-poor-pyrite-limestone", "file": "game:itemtypes/resource/ore-graded.json", "dependsOn": [{ "modid": "geoaddons" }] },
  { "op": "add", "path": "/allowedVariants/-", "value": "ore-medium-pyrite-limestone", "file": "game:itemtypes/resource/ore-graded.json", "dependsOn": [{ "modid": "geoaddons" }] },
  { "op": "add", "path": "/allowedVariants/-", "value": "ore-poor-pyrite-andesite", "file": "game:itemtypes/resource/ore-graded.json", "dependsOn": [{ "modid": "geoaddons" }] },
  { "op": "add", "path": "/allowedVariants/-", "value": "ore-medium-pyrite-andesite", "file": "game:itemtypes/resource/ore-graded.json", "dependsOn": [{ "modid": "geoaddons" }] },
  { "op": "add", "path": "/allowedVariants/-", "value": "ore-poor-pyrite-granite", "file": "game:itemtypes/resource/ore-graded.json", "dependsOn": [{ "modid": "geoaddons" }] },
  { "op": "add", "path": "/allowedVariants/-", "value": "ore-medium-pyrite-granite", "file": "game:itemtypes/resource/ore-graded.json", "dependsOn": [{ "modid": "geoaddons" }] },
  { "op": "add", "path": "/allowedVariants/-", "value": "ore-poor-pyrite-peridotite", "file": "game:itemtypes/resource/ore-graded.json", "dependsOn": [{ "modid": "geoaddons" }] },
  { "op": "add", "path": "/allowedVariants/-", "value": "ore-medium-pyrite-peridotite", "file": "game:itemtypes/resource/ore-graded.json", "dependsOn": [{ "modid": "geoaddons" }] },
  { "op": "add", "path": "/allowedVariants/-", "value": "ore-poor-pyrite-gneiss", "file": "game:itemtypes/resource/ore-graded.json", "dependsOn": [{ "modid": "geoaddons" }] },
  { "op": "add", "path": "/allowedVariants/-", "value": "ore-medium-pyrite-gneiss", "file": "game:itemtypes/resource/ore-graded.json", "dependsOn": [{ "modid": "geoaddons" }] },
  { "op": "add", "path": "/allowedVariants/-", "value": "ore-poor-pyrite-schist", "file": "game:itemtypes/resource/ore-graded.json", "dependsOn": [{ "modid": "geoaddons" }] },
  { "op": "add", "path": "/allowedVariants/-", "value": "ore-medium-pyrite-schist", "file": "game:itemtypes/resource/ore-graded.json", "dependsOn": [{ "modid": "geoaddons" }] },
  { "op": "add", "path": "/allowedVariants/-", "value": "ore-poor-pyrite-diorite", "file": "game:itemtypes/resource/ore-graded.json", "dependsOn": [{ "modid": "geoaddons" }] },
  { "op": "add", "path": "/allowedVariants/-", "value": "ore-medium-pyrite-diorite", "file": "game:itemtypes/resource/ore-graded.json", "dependsOn": [{ "modid": "geoaddons" }] },
  { "op": "add", "path": "/allowedVariants/-", "value": "ore-poor-pyrite-gabbro", "file": "game:itemtypes/resource/ore-graded.json", "dependsOn": [{ "modid": "geoaddons" }] },
  { "op": "add", "path": "/allowedVariants/-", "value": "ore-medium-pyrite-gabbro", "file": "game:itemtypes/resource/ore-graded.json", "dependsOn": [{ "modid": "geoaddons" }] },
  { "op": "add", "path": "/allowedVariants/-", "value": "ore-poor-pyrite-dacite", "file": "game:itemtypes/resource/ore-graded.json", "dependsOn": [{ "modid": "geoaddons" }] },
  { "op": "add", "path": "/allowedVariants/-", "value": "ore-medium-pyrite-dacite", "file": "game:itemtypes/resource/ore-graded.json", "dependsOn": [{ "modid": "geoaddons" }] },
  { "op": "add", "path": "/allowedVariants/-", "value": "ore-poor-pyrite-rhyolite", "file": "game:itemtypes/resource/ore-graded.json", "dependsOn": [{ "modid": "geoaddons" }] },
  { "op": "add", "path": "/allowedVariants/-", "value": "ore-medium-pyrite-rhyolite", "file": "game:itemtypes/resource/ore-graded.json", "dependsOn": [{ "modid": "geoaddons" }] },
  // --- pyrite: crystalizedore-graded ---
  { "op": "add", "path": "/allowedVariants/-", "value": "crystalizedore-poor-pyrite-sandstone", "file": "game:itemtypes/resource/crystalizedore-graded.json", "dependsOn": [{ "modid": "geoaddons" }] },
  { "op": "add", "path": "/allowedVariants/-", "value": "crystalizedore-medium-pyrite-sandstone", "file": "game:itemtypes/resource/crystalizedore-graded.json", "dependsOn": [{ "modid": "geoaddons" }] },
  { "op": "add", "path": "/allowedVariants/-", "value": "crystalizedore-poor-pyrite-shale", "file": "game:itemtypes/resource/crystalizedore-graded.json", "dependsOn": [{ "modid": "geoaddons" }] },
  { "op": "add", "path": "/allowedVariants/-", "value": "crystalizedore-medium-pyrite-shale", "file": "game:itemtypes/resource/crystalizedore-graded.json", "dependsOn": [{ "modid": "geoaddons" }] },
  { "op": "add", "path": "/allowedVariants/-", "value": "crystalizedore-poor-pyrite-limestone", "file": "game:itemtypes/resource/crystalizedore-graded.json", "dependsOn": [{ "modid": "geoaddons" }] },
  { "op": "add", "path": "/allowedVariants/-", "value": "crystalizedore-medium-pyrite-limestone", "file": "game:itemtypes/resource/crystalizedore-graded.json", "dependsOn": [{ "modid": "geoaddons" }] },
  { "op": "add", "path": "/allowedVariants/-", "value": "crystalizedore-poor-pyrite-andesite", "file": "game:itemtypes/resource/crystalizedore-graded.json", "dependsOn": [{ "modid": "geoaddons" }] },
  { "op": "add", "path": "/allowedVariants/-", "value": "crystalizedore-medium-pyrite-andesite", "file": "game:itemtypes/resource/crystalizedore-graded.json", "dependsOn": [{ "modid": "geoaddons" }] },
  { "op": "add", "path": "/allowedVariants/-", "value": "crystalizedore-poor-pyrite-granite", "file": "game:itemtypes/resource/crystalizedore-graded.json", "dependsOn": [{ "modid": "geoaddons" }] },
  { "op": "add", "path": "/allowedVariants/-", "value": "crystalizedore-medium-pyrite-granite", "file": "game:itemtypes/resource/crystalizedore-graded.json", "dependsOn": [{ "modid": "geoaddons" }] },
  { "op": "add", "path": "/allowedVariants/-", "value": "crystalizedore-poor-pyrite-peridotite", "file": "game:itemtypes/resource/crystalizedore-graded.json", "dependsOn": [{ "modid": "geoaddons" }] },
  { "op": "add", "path": "/allowedVariants/-", "value": "crystalizedore-medium-pyrite-peridotite", "file": "game:itemtypes/resource/crystalizedore-graded.json", "dependsOn": [{ "modid": "geoaddons" }] },
  { "op": "add", "path": "/allowedVariants/-", "value": "crystalizedore-poor-pyrite-gneiss", "file": "game:itemtypes/resource/crystalizedore-graded.json", "dependsOn": [{ "modid": "geoaddons" }] },
  { "op": "add", "path": "/allowedVariants/-", "value": "crystalizedore-medium-pyrite-gneiss", "file": "game:itemtypes/resource/crystalizedore-graded.json", "dependsOn": [{ "modid": "geoaddons" }] },
  { "op": "add", "path": "/allowedVariants/-", "value": "crystalizedore-poor-pyrite-schist", "file": "game:itemtypes/resource/crystalizedore-graded.json", "dependsOn": [{ "modid": "geoaddons" }] },
  { "op": "add", "path": "/allowedVariants/-", "value": "crystalizedore-medium-pyrite-schist", "file": "game:itemtypes/resource/crystalizedore-graded.json", "dependsOn": [{ "modid": "geoaddons" }] },
  { "op": "add", "path": "/allowedVariants/-", "value": "crystalizedore-poor-pyrite-diorite", "file": "game:itemtypes/resource/crystalizedore-graded.json", "dependsOn": [{ "modid": "geoaddons" }] },
  { "op": "add", "path": "/allowedVariants/-", "value": "crystalizedore-medium-pyrite-diorite", "file": "game:itemtypes/resource/crystalizedore-graded.json", "dependsOn": [{ "modid": "geoaddons" }] },
  { "op": "add", "path": "/allowedVariants/-", "value": "crystalizedore-poor-pyrite-gabbro", "file": "game:itemtypes/resource/crystalizedore-graded.json", "dependsOn": [{ "modid": "geoaddons" }] },
  { "op": "add", "path": "/allowedVariants/-", "value": "crystalizedore-medium-pyrite-gabbro", "file": "game:itemtypes/resource/crystalizedore-graded.json", "dependsOn": [{ "modid": "geoaddons" }] },
  { "op": "add", "path": "/allowedVariants/-", "value": "crystalizedore-poor-pyrite-dacite", "file": "game:itemtypes/resource/crystalizedore-graded.json", "dependsOn": [{ "modid": "geoaddons" }] },
  { "op": "add", "path": "/allowedVariants/-", "value": "crystalizedore-medium-pyrite-dacite", "file": "game:itemtypes/resource/crystalizedore-graded.json", "dependsOn": [{ "modid": "geoaddons" }] },
  { "op": "add", "path": "/allowedVariants/-", "value": "crystalizedore-poor-pyrite-rhyolite", "file": "game:itemtypes/resource/crystalizedore-graded.json", "dependsOn": [{ "modid": "geoaddons" }] },
  { "op": "add", "path": "/allowedVariants/-", "value": "crystalizedore-medium-pyrite-rhyolite", "file": "game:itemtypes/resource/crystalizedore-graded.json", "dependsOn": [{ "modid": "geoaddons" }] },

  // ==== IOG+GEOADDONS: Register variants for IOG's GeoAddons chalcopyrite deposit ====
  // These resolve "No block with code/wildcard was found" warnings from IOG's GeoAddons compat
  // entry in interestingoregen:worldgen/deposits/metalore/chalcopyrite.json

  // --- chalcopyrite: blocktypes/ore-graded ---
  { "op": "add", "path": "/allowedVariants/-", "value": "ore-rich-chalcopyrite-limestone", "file": "game:blocktypes/stone/ore-graded.json", "dependsOn": [{ "modid": "interestingoregen" }, { "modid": "geoaddons" }] },
  { "op": "add", "path": "/allowedVariants/-", "value": "ore-bountiful-chalcopyrite-limestone", "file": "game:blocktypes/stone/ore-graded.json", "dependsOn": [{ "modid": "interestingoregen" }, { "modid": "geoaddons" }] },
  { "op": "add", "path": "/allowedVariants/-", "value": "ore-poor-chalcopyrite-dolostone", "file": "game:blocktypes/stone/ore-graded.json", "dependsOn": [{ "modid": "interestingoregen" }, { "modid": "geoaddons" }] },
  { "op": "add", "path": "/allowedVariants/-", "value": "ore-medium-chalcopyrite-dolostone", "file": "game:blocktypes/stone/ore-graded.json", "dependsOn": [{ "modid": "interestingoregen" }, { "modid": "geoaddons" }] },
  { "op": "add", "path": "/allowedVariants/-", "value": "ore-rich-chalcopyrite-dolostone", "file": "game:blocktypes/stone/ore-graded.json", "dependsOn": [{ "modid": "interestingoregen" }, { "modid": "geoaddons" }] },
  { "op": "add", "path": "/allowedVariants/-", "value": "ore-bountiful-chalcopyrite-dolostone", "file": "game:blocktypes/stone/ore-graded.json", "dependsOn": [{ "modid": "interestingoregen" }, { "modid": "geoaddons" }] },
  { "op": "add", "path": "/allowedVariants/-", "value": "ore-poor-chalcopyrite-chalk", "file": "game:blocktypes/stone/ore-graded.json", "dependsOn": [{ "modid": "interestingoregen" }, { "modid": "geoaddons" }] },
  { "op": "add", "path": "/allowedVariants/-", "value": "ore-medium-chalcopyrite-chalk", "file": "game:blocktypes/stone/ore-graded.json", "dependsOn": [{ "modid": "interestingoregen" }, { "modid": "geoaddons" }] },
  { "op": "add", "path": "/allowedVariants/-", "value": "ore-rich-chalcopyrite-chalk", "file": "game:blocktypes/stone/ore-graded.json", "dependsOn": [{ "modid": "interestingoregen" }, { "modid": "geoaddons" }] },
  { "op": "add", "path": "/allowedVariants/-", "value": "ore-bountiful-chalcopyrite-chalk", "file": "game:blocktypes/stone/ore-graded.json", "dependsOn": [{ "modid": "interestingoregen" }, { "modid": "geoaddons" }] },
  { "op": "add", "path": "/allowedVariants/-", "value": "ore-poor-chalcopyrite-basalt", "file": "game:blocktypes/stone/ore-graded.json", "dependsOn": [{ "modid": "interestingoregen" }, { "modid": "geoaddons" }] },
  { "op": "add", "path": "/allowedVariants/-", "value": "ore-medium-chalcopyrite-basalt", "file": "game:blocktypes/stone/ore-graded.json", "dependsOn": [{ "modid": "interestingoregen" }, { "modid": "geoaddons" }] },
  { "op": "add", "path": "/allowedVariants/-", "value": "ore-poor-chalcopyrite-phyllite", "file": "game:blocktypes/stone/ore-graded.json", "dependsOn": [{ "modid": "interestingoregen" }, { "modid": "geoaddons" }] },
  { "op": "add", "path": "/allowedVariants/-", "value": "ore-medium-chalcopyrite-phyllite", "file": "game:blocktypes/stone/ore-graded.json", "dependsOn": [{ "modid": "interestingoregen" }, { "modid": "geoaddons" }] },
  { "op": "add", "path": "/allowedVariants/-", "value": "ore-poor-chalcopyrite-amphibolite", "file": "game:blocktypes/stone/ore-graded.json", "dependsOn": [{ "modid": "interestingoregen" }, { "modid": "geoaddons" }] },
  // --- chalcopyrite: itemtypes/ore-graded ---
  { "op": "add", "path": "/allowedVariants/-", "value": "ore-rich-chalcopyrite-limestone", "file": "game:itemtypes/resource/ore-graded.json", "dependsOn": [{ "modid": "interestingoregen" }, { "modid": "geoaddons" }] },
  { "op": "add", "path": "/allowedVariants/-", "value": "ore-bountiful-chalcopyrite-limestone", "file": "game:itemtypes/resource/ore-graded.json", "dependsOn": [{ "modid": "interestingoregen" }, { "modid": "geoaddons" }] },
  { "op": "add", "path": "/allowedVariants/-", "value": "ore-poor-chalcopyrite-dolostone", "file": "game:itemtypes/resource/ore-graded.json", "dependsOn": [{ "modid": "interestingoregen" }, { "modid": "geoaddons" }] },
  { "op": "add", "path": "/allowedVariants/-", "value": "ore-medium-chalcopyrite-dolostone", "file": "game:itemtypes/resource/ore-graded.json", "dependsOn": [{ "modid": "interestingoregen" }, { "modid": "geoaddons" }] },
  { "op": "add", "path": "/allowedVariants/-", "value": "ore-rich-chalcopyrite-dolostone", "file": "game:itemtypes/resource/ore-graded.json", "dependsOn": [{ "modid": "interestingoregen" }, { "modid": "geoaddons" }] },
  { "op": "add", "path": "/allowedVariants/-", "value": "ore-bountiful-chalcopyrite-dolostone", "file": "game:itemtypes/resource/ore-graded.json", "dependsOn": [{ "modid": "interestingoregen" }, { "modid": "geoaddons" }] },
  { "op": "add", "path": "/allowedVariants/-", "value": "ore-poor-chalcopyrite-chalk", "file": "game:itemtypes/resource/ore-graded.json", "dependsOn": [{ "modid": "interestingoregen" }, { "modid": "geoaddons" }] },
  { "op": "add", "path": "/allowedVariants/-", "value": "ore-medium-chalcopyrite-chalk", "file": "game:itemtypes/resource/ore-graded.json", "dependsOn": [{ "modid": "interestingoregen" }, { "modid": "geoaddons" }] },
  { "op": "add", "path": "/allowedVariants/-", "value": "ore-rich-chalcopyrite-chalk", "file": "game:itemtypes/resource/ore-graded.json", "dependsOn": [{ "modid": "interestingoregen" }, { "modid": "geoaddons" }] },
  { "op": "add", "path": "/allowedVariants/-", "value": "ore-bountiful-chalcopyrite-chalk", "file": "game:itemtypes/resource/ore-graded.json", "dependsOn": [{ "modid": "interestingoregen" }, { "modid": "geoaddons" }] },
  { "op": "add", "path": "/allowedVariants/-", "value": "ore-poor-chalcopyrite-basalt", "file": "game:itemtypes/resource/ore-graded.json", "dependsOn": [{ "modid": "interestingoregen" }, { "modid": "geoaddons" }] },
  { "op": "add", "path": "/allowedVariants/-", "value": "ore-medium-chalcopyrite-basalt", "file": "game:itemtypes/resource/ore-graded.json", "dependsOn": [{ "modid": "interestingoregen" }, { "modid": "geoaddons" }] },
  { "op": "add", "path": "/allowedVariants/-", "value": "ore-poor-chalcopyrite-phyllite", "file": "game:itemtypes/resource/ore-graded.json", "dependsOn": [{ "modid": "interestingoregen" }, { "modid": "geoaddons" }] },
  { "op": "add", "path": "/allowedVariants/-", "value": "ore-medium-chalcopyrite-phyllite", "file": "game:itemtypes/resource/ore-graded.json", "dependsOn": [{ "modid": "interestingoregen" }, { "modid": "geoaddons" }] },
  { "op": "add", "path": "/allowedVariants/-", "value": "ore-poor-chalcopyrite-amphibolite", "file": "game:itemtypes/resource/ore-graded.json", "dependsOn": [{ "modid": "interestingoregen" }, { "modid": "geoaddons" }] },
  // --- chalcopyrite: crystalizedore-graded ---
  { "op": "add", "path": "/allowedVariants/-", "value": "crystalizedore-rich-chalcopyrite-limestone", "file": "game:itemtypes/resource/crystalizedore-graded.json", "dependsOn": [{ "modid": "interestingoregen" }, { "modid": "geoaddons" }] },
  { "op": "add", "path": "/allowedVariants/-", "value": "crystalizedore-bountiful-chalcopyrite-limestone", "file": "game:itemtypes/resource/crystalizedore-graded.json", "dependsOn": [{ "modid": "interestingoregen" }, { "modid": "geoaddons" }] },
  { "op": "add", "path": "/allowedVariants/-", "value": "crystalizedore-poor-chalcopyrite-dolostone", "file": "game:itemtypes/resource/crystalizedore-graded.json", "dependsOn": [{ "modid": "interestingoregen" }, { "modid": "geoaddons" }] },
  { "op": "add", "path": "/allowedVariants/-", "value": "crystalizedore-medium-chalcopyrite-dolostone", "file": "game:itemtypes/resource/crystalizedore-graded.json", "dependsOn": [{ "modid": "interestingoregen" }, { "modid": "geoaddons" }] },
  { "op": "add", "path": "/allowedVariants/-", "value": "crystalizedore-rich-chalcopyrite-dolostone", "file": "game:itemtypes/resource/crystalizedore-graded.json", "dependsOn": [{ "modid": "interestingoregen" }, { "modid": "geoaddons" }] },
  { "op": "add", "path": "/allowedVariants/-", "value": "crystalizedore-bountiful-chalcopyrite-dolostone", "file": "game:itemtypes/resource/crystalizedore-graded.json", "dependsOn": [{ "modid": "interestingoregen" }, { "modid": "geoaddons" }] },
  { "op": "add", "path": "/allowedVariants/-", "value": "crystalizedore-poor-chalcopyrite-chalk", "file": "game:itemtypes/resource/crystalizedore-graded.json", "dependsOn": [{ "modid": "interestingoregen" }, { "modid": "geoaddons" }] },
  { "op": "add", "path": "/allowedVariants/-", "value": "crystalizedore-medium-chalcopyrite-chalk", "file": "game:itemtypes/resource/crystalizedore-graded.json", "dependsOn": [{ "modid": "interestingoregen" }, { "modid": "geoaddons" }] },
  { "op": "add", "path": "/allowedVariants/-", "value": "crystalizedore-rich-chalcopyrite-chalk", "file": "game:itemtypes/resource/crystalizedore-graded.json", "dependsOn": [{ "modid": "interestingoregen" }, { "modid": "geoaddons" }] },
  { "op": "add", "path": "/allowedVariants/-", "value": "crystalizedore-bountiful-chalcopyrite-chalk", "file": "game:itemtypes/resource/crystalizedore-graded.json", "dependsOn": [{ "modid": "interestingoregen" }, { "modid": "geoaddons" }] },
  { "op": "add", "path": "/allowedVariants/-", "value": "crystalizedore-poor-chalcopyrite-basalt", "file": "game:itemtypes/resource/crystalizedore-graded.json", "dependsOn": [{ "modid": "interestingoregen" }, { "modid": "geoaddons" }] },
  { "op": "add", "path": "/allowedVariants/-", "value": "crystalizedore-medium-chalcopyrite-basalt", "file": "game:itemtypes/resource/crystalizedore-graded.json", "dependsOn": [{ "modid": "interestingoregen" }, { "modid": "geoaddons" }] },
  { "op": "add", "path": "/allowedVariants/-", "value": "crystalizedore-poor-chalcopyrite-phyllite", "file": "game:itemtypes/resource/crystalizedore-graded.json", "dependsOn": [{ "modid": "interestingoregen" }, { "modid": "geoaddons" }] },
  { "op": "add", "path": "/allowedVariants/-", "value": "crystalizedore-medium-chalcopyrite-phyllite", "file": "game:itemtypes/resource/crystalizedore-graded.json", "dependsOn": [{ "modid": "interestingoregen" }, { "modid": "geoaddons" }] },
  { "op": "add", "path": "/allowedVariants/-", "value": "crystalizedore-poor-chalcopyrite-amphibolite", "file": "game:itemtypes/resource/crystalizedore-graded.json", "dependsOn": [{ "modid": "interestingoregen" }, { "modid": "geoaddons" }] }
]
